{
  "$schema": "http://interagent.github.io/interagent-hyper-schema",
  "type": [
    "object"
  ],
  "definitions": {
    "ja_era": {
      "$schema": "http://json-schema.org/draft-04/hyper-schema",
      "title": "JaEra",
      "description": "API to return list of Japanese era code and names. (JISX0301)",
      "stability": "prototype",
      "strictProperties": true,
      "type": [
        "object"
      ],
      "definitions": {
        "code": {
          "description": "unique identifier of Japanese era",
          "example": 1,
          "readOnly": true,
          "type": [
            "integer"
          ]
        },
        "name": {
          "description": "unique name of Japanese era",
          "example": "明治",
          "readOnly": true,
          "type": [
            "string"
          ]
        },
        "start_date": {
          "description": "date the era started",
          "example": "1868-01-25",
          "type": [
            "string"
          ]
        },
        "identity": {
          "anyOf": [
            {
              "$ref": "#/definitions/ja_era/definitions/code"
            },
            {
              "$ref": "#/definitions/ja_era/definitions/name"
            }
          ]
        }
      },
      "links": [
        {
          "description": "List existing Japanese era names.",
          "href": "/ja_eras",
          "method": "GET",
          "rel": "instances",
          "title": "List"
        }
      ],
      "properties": {
        "code": {
          "$ref": "#/definitions/ja_era/definitions/code"
        },
        "name": {
          "$ref": "#/definitions/ja_era/definitions/name"
        },
        "start_date": {
          "$ref": "#/definitions/ja_era/definitions/start_date"
        }
      }
    },
    "prefecture": {
      "$schema": "http://json-schema.org/draft-04/hyper-schema",
      "title": "Prefecture",
      "description": "API to return list of Prefecture code and names set. (JISX0401)",
      "stability": "prototype",
      "strictProperties": true,
      "type": [
        "object"
      ],
      "definitions": {
        "code": {
          "description": "unique identifier of Prefecture.",
          "example": 1,
          "readOnly": true,
          "type": [
            "string"
          ]
        },
        "code_bo": {
          "description": "unique identifier of Prefecture, using bo.",
          "example": 1,
          "readOnly": true,
          "type": [
            "integer"
          ]
        },
        "name": {
          "description": "unique name of Prefecture",
          "example": "北海道",
          "readOnly": true,
          "type": [
            "string"
          ]
        },
        "identity": {
          "anyOf": [
            {
              "$ref": "#/definitions/prefecture/definitions/code"
            },
            {
              "$ref": "#/definitions/prefecture/definitions/name"
            }
          ]
        }
      },
      "links": [
        {
          "description": "List existing prefectures.",
          "href": "/prefectures",
          "method": "GET",
          "rel": "instances",
          "title": "List"
        }
      ],
      "properties": {
        "code": {
          "$ref": "#/definitions/prefecture/definitions/code"
        },
        "code_bo": {
          "$ref": "#/definitions/prefecture/definitions/code_bo"
        },
        "name": {
          "$ref": "#/definitions/prefecture/definitions/name"
        }
      }
    }
  },
  "properties": {
    "ja_era": {
      "$ref": "#/definitions/ja_era"
    },
    "prefecture": {
      "$ref": "#/definitions/prefecture"
    }
  }
}
